bookmarklets/__init__.py
bookmarklets/__main__.py
bookmarklets/bookmarklet.py
bookmarklets/metadata.py
bookmarklets-0.3.2.dist-info/entry_points.txt
bookmarklets-0.3.2.dist-info/METADATA
bookmarklets-0.3.2.dist-info/WHEEL
bookmarklets-0.3.2.dist-info/RECORD
