Metadata-Version: 2.1
Name: bookmarklets
Version: 0.3.2
Summary: Tool to develop bookmarklets
Home-page: https://github.com/skarfie123/bookmarklets
Author: skarfie123
Author-email: rahulpai@rocketmail.com
Requires-Python: >=3.10,<4.0
Classifier: Programming Language :: Python :: 3
Classifier: Programming Language :: Python :: 3.10
Classifier: Programming Language :: Python :: 3.11
Requires-Dist: fastapi (>=0.103.2,<0.104.0)
Requires-Dist: typer[all] (>=0.9.0,<0.10.0)
Requires-Dist: uvicorn[standard] (>=0.23.2,<0.24.0)
Project-URL: Repository, https://github.com/skarfie123/bookmarklets
